odoo/addons/web_tree_many2one_clickable/README.rst
odoo/addons/web_tree_many2one_clickable/__init__.py
odoo/addons/web_tree_many2one_clickable/__manifest__.py
odoo/addons/web_tree_many2one_clickable/i18n/it.po
odoo/addons/web_tree_many2one_clickable/i18n/web_tree_many2one_clickable.pot
odoo/addons/web_tree_many2one_clickable/i18n/zh_CN.po
odoo/addons/web_tree_many2one_clickable/readme/CONFIGURATION.rst
odoo/addons/web_tree_many2one_clickable/readme/CONTRIBUTORS.rst
odoo/addons/web_tree_many2one_clickable/readme/DESCRIPTION.rst
odoo/addons/web_tree_many2one_clickable/readme/ROADMAP.rst
odoo/addons/web_tree_many2one_clickable/readme/USAGE.rst
odoo/addons/web_tree_many2one_clickable/static/description/icon.png
odoo/addons/web_tree_many2one_clickable/static/description/index.html
odoo/addons/web_tree_many2one_clickable/static/img/clickable.gif
odoo/addons/web_tree_many2one_clickable/static/src/css/web_tree_many2one_clickable.scss
odoo/addons/web_tree_many2one_clickable/static/src/js/web_tree_many2one_clickable.js
odoo/addons/web_tree_many2one_clickable/views/assets.xml
odoo14_addon_web_tree_many2one_clickable-14.0.1.0.3.dist-info/METADATA
odoo14_addon_web_tree_many2one_clickable-14.0.1.0.3.dist-info/WHEEL
odoo14_addon_web_tree_many2one_clickable-14.0.1.0.3.dist-info/top_level.txt
odoo14_addon_web_tree_many2one_clickable-14.0.1.0.3.dist-info/RECORD
